{
  "schema_version": 1,
  "predecessor_commit": "1c3f3ca758d1",
  "declared_objective": {
    "board": "core_cpu",
    "workload_class": "wide",
    "dimension": "time"
  },
  "declared_scope": "s3",
  "files": {
    "src/core/fields/qm31.zig": "sha256:5c546b9e274660d85e32c983f099a687781b77f5c959a7a9cf571ec21c5bc3e0"
  },
  "transcripts": {
    "transcripts/session-01.md": {
      "sha256": "5e8066ad282804965f71f683f2ca94a87cfaa61ad9c698256f7de3f9bf23907f",
      "captured_by": "submitter"
    }
  },
  "transcripts_declined": false
}
