{
  "evidence_phases": {
    "benchmark": ["BG-12", "BG-14"],
    "build_performance_memory": ["BG-00", "BG-14"],
    "compatibility": ["BG-08"],
    "import_closure": ["BG-01", "BG-02", "BG-03", "BG-04", "BG-05", "BG-06", "BG-07", "BG-08", "BG-09"],
    "link_closure": ["BG-03", "BG-04", "BG-05", "BG-08"],
    "oracle": ["BG-13"],
    "source_conformance": ["BG-09"],
    "source_debt": ["BG-00", "BG-09"]
  },
  "optimize": "ReleaseFast",
  "roles": {
    "linux": {
      "commands": [
        {"id": "baseline", "phase": "BG-00", "argv": ["python3", "scripts/check_build_monorepo_baseline.py"], "required_inputs": ["conformance/build-monorepo-baseline-v1.json"], "generated_outputs": []},
        {"id": "product-matrix", "phase": "BG-01", "argv": ["zig", "build", "product-matrix-identity", "-Doptimize=ReleaseFast"], "required_inputs": [], "generated_outputs": ["zig-out/identity/product-matrix.json"]},
        {"id": "core-prover", "phase": "BG-02", "argv": ["zig", "build", "test-stwo-core", "test-stwo-prover", "test-downstream-modules", "identity-stwo-core", "identity-stwo-prover", "-Doptimize=ReleaseFast"], "required_inputs": [], "generated_outputs": ["zig-out/identity/stwo-core.json", "zig-out/identity/stwo-prover.json"]},
        {"id": "riscv-product", "phase": "BG-03", "argv": ["zig", "build", "test-riscv-cpu-product", "riscv-trace-dump", "stwo-zig-riscv-cpu", "stwo-zig-riscv-cpu-static", "-Doptimize=ReleaseFast"], "required_inputs": [], "generated_outputs": ["zig-out/bin/riscv-trace-dump", "zig-out/bin/stwo-zig-riscv-cpu", "zig-out/bin/stwo-zig-riscv-cpu-x86_64-linux-musl"]},
        {"id": "riscv-applications", "phase": "BG-03", "argv": ["zig-out/bin/stwo-zig-riscv-cpu", "applications"], "required_inputs": ["zig-out/bin/stwo-zig-riscv-cpu"], "generated_outputs": []},
        {"id": "riscv-link-closure", "phase": "BG-03", "argv": ["python3", "scripts/check_architecture_link_closure.py", "--product", "stwo-riscv-cpu", "--binary", "zig-out/bin/stwo-zig-riscv-cpu", "--static-binary", "zig-out/bin/stwo-zig-riscv-cpu-x86_64-linux-musl", "--output", "{evidence_dir}/riscv-link-closure.json"], "required_inputs": ["zig-out/bin/stwo-zig-riscv-cpu", "zig-out/bin/stwo-zig-riscv-cpu-x86_64-linux-musl"], "generated_outputs": ["{evidence_dir}/riscv-link-closure.json"]},
        {"id": "riscv-fast-challenge-issue", "phase": "BG-03", "argv": ["python3", "scripts/riscv_release_challenge.py", "issue", "--bundle", "{riscv_bundle}", "--repository", "{repository}", "--repository-id", "{repository_id}", "--candidate", "{candidate}", "--tree", "{tree}", "--phase", "{riscv_phase}", "--workflow-sha", "{workflow_sha}", "--run-id", "{run_id}", "--run-attempt", "{run_attempt}", "--cli", "zig-out/bin/stwo-zig-riscv-cpu-x86_64-linux-musl", "--trace-cli", "zig-out/bin/riscv-trace-dump", "--output", "{evidence_dir}/riscv-challenge.json"], "required_inputs": ["{riscv_bundle}/manifest.json", "zig-out/bin/stwo-zig-riscv-cpu-x86_64-linux-musl", "zig-out/bin/riscv-trace-dump"], "generated_outputs": ["{evidence_dir}/riscv-challenge.json"]},
        {"id": "riscv-fast-challenge-execute", "phase": "BG-03", "argv": ["python3", "scripts/riscv_release_challenge.py", "execute", "--bundle", "{riscv_bundle}", "--repository", "{repository}", "--repository-id", "{repository_id}", "--candidate", "{candidate}", "--tree", "{tree}", "--phase", "{riscv_phase}", "--workflow-sha", "{workflow_sha}", "--run-id", "{run_id}", "--run-attempt", "{run_attempt}", "--cli", "zig-out/bin/stwo-zig-riscv-cpu-x86_64-linux-musl", "--trace-cli", "zig-out/bin/riscv-trace-dump", "--challenge", "{evidence_dir}/riscv-challenge.json", "--evidence-dir", "{evidence_dir}/riscv-fast", "--replay-ledger", "{evidence_dir}/riscv-replay", "--result", "{evidence_dir}/riscv-fast/result.json"], "required_inputs": ["{riscv_bundle}/manifest.json", "{evidence_dir}/riscv-challenge.json", "zig-out/bin/stwo-zig-riscv-cpu-x86_64-linux-musl", "zig-out/bin/riscv-trace-dump"], "generated_outputs": ["{evidence_dir}/riscv-fast/result.json"]},
        {"id": "native-cpu-product", "phase": "BG-04", "argv": ["zig", "build", "test-native-cpu-product", "stwo-native-cpu", "benchmark-native-cpu", "-Doptimize=ReleaseFast"], "required_inputs": [], "generated_outputs": ["zig-out/bin/stwo-zig-native-cpu", "zig-out/bin/stwo-zig-native-cpu-bench"]},
        {"id": "native-cpu-applications", "phase": "BG-04", "argv": ["zig-out/bin/stwo-zig-native-cpu", "applications"], "required_inputs": ["zig-out/bin/stwo-zig-native-cpu"], "generated_outputs": []},
        {"id": "native-cpu-link-closure", "phase": "BG-04", "argv": ["python3", "scripts/check_architecture_link_closure.py", "--product", "stwo-native-cpu", "--binary", "zig-out/bin/stwo-zig-native-cpu", "--output", "{evidence_dir}/native-cpu-link-closure.json"], "required_inputs": ["zig-out/bin/stwo-zig-native-cpu"], "generated_outputs": ["{evidence_dir}/native-cpu-link-closure.json"]},
        {"id": "cuda-policy", "phase": "BG-06", "argv": ["zig", "test", "build_support/product_policy_test.zig", "-OReleaseFast"], "required_inputs": [], "generated_outputs": []},
        {"id": "deferred-products", "phase": "BG-07", "argv": ["zig", "test", "build_support/product_policy_test.zig", "-OReleaseFast"], "required_inputs": [], "generated_outputs": []},
        {"id": "aggregate", "phase": "BG-08", "argv": ["zig", "build", "stwo-zig", "test", "identity-stwo-zig", "-Daggregate-metal=false", "-Doptimize=ReleaseFast"], "required_inputs": [], "generated_outputs": ["zig-out/bin/stwo-zig", "zig-out/identity/stwo-zig.json"]},
        {"id": "aggregate-link-closure", "phase": "BG-08", "argv": ["python3", "scripts/check_architecture_link_closure.py", "--product", "stwo-zig", "--binary", "zig-out/bin/stwo-zig", "--output", "{evidence_dir}/aggregate-link-closure.json"], "required_inputs": ["zig-out/bin/stwo-zig"], "generated_outputs": ["{evidence_dir}/aggregate-link-closure.json"]},
        {"id": "focused-parity-prove", "phase": "BG-08", "argv": ["zig-out/bin/stwo-zig-native-cpu", "prove", "--example", "wide_fibonacci", "--log-n-rows", "8", "--sequence-len", "8", "--protocol", "smoke", "--profiled", "--output", "{evidence_dir}/focused-proof.json", "--report-out", "{evidence_dir}/focused-report.json"], "required_inputs": ["zig-out/bin/stwo-zig-native-cpu"], "generated_outputs": ["{evidence_dir}/focused-proof.json", "{evidence_dir}/focused-report.json"]},
        {"id": "aggregate-parity-prove", "phase": "BG-08", "argv": ["zig-out/bin/stwo-zig", "prove", "--air", "wide_fibonacci", "--backend", "cpu", "--log-n-rows", "8", "--sequence-len", "8", "--protocol", "smoke", "--profiled", "--output", "{evidence_dir}/aggregate-proof.json", "--report-out", "{evidence_dir}/aggregate-report.json"], "required_inputs": ["zig-out/bin/stwo-zig"], "generated_outputs": ["{evidence_dir}/aggregate-proof.json", "{evidence_dir}/aggregate-report.json"]},
        {"id": "focused-parity-verify", "phase": "BG-08", "argv": ["zig-out/bin/stwo-zig-native-cpu", "verify", "--artifact", "{evidence_dir}/focused-proof.json", "--protocol", "smoke"], "required_inputs": ["zig-out/bin/stwo-zig-native-cpu", "{evidence_dir}/focused-proof.json"], "generated_outputs": []},
        {"id": "aggregate-parity-verify", "phase": "BG-08", "argv": ["zig-out/bin/stwo-zig", "verify", "--artifact", "{evidence_dir}/aggregate-proof.json", "--protocol", "smoke"], "required_inputs": ["zig-out/bin/stwo-zig", "{evidence_dir}/aggregate-proof.json"], "generated_outputs": []},
        {"id": "aggregate-parity-compare", "phase": "BG-08", "argv": ["python3", "scripts/check_aggregate_parity.py", "--focused", "{evidence_dir}/focused-proof.json", "--aggregate", "{evidence_dir}/aggregate-proof.json", "--focused-report", "{evidence_dir}/focused-report.json", "--aggregate-report", "{evidence_dir}/aggregate-report.json", "--focused-verify", "{stdout_focused_parity_verify}", "--aggregate-verify", "{stdout_aggregate_parity_verify}", "--output", "{evidence_dir}/aggregate-parity.json"], "required_inputs": ["{evidence_dir}/focused-proof.json", "{evidence_dir}/aggregate-proof.json", "{evidence_dir}/focused-report.json", "{evidence_dir}/aggregate-report.json", "{stdout_focused_parity_verify}", "{stdout_aggregate_parity_verify}"], "generated_outputs": ["{evidence_dir}/aggregate-parity.json"]},
        {"id": "configure-closure", "phase": "BG-09", "argv": ["zig", "build", "build-configure-closure", "-Doptimize=ReleaseFast"], "required_inputs": [], "generated_outputs": ["zig-out/build-graph/configure-closure.json"]},
        {"id": "source-conformance", "phase": "BG-09", "argv": ["python3", "scripts/check_source_conformance.py"], "required_inputs": ["conformance/source-baseline.json"], "generated_outputs": []},
        {"id": "identity-mutations", "phase": "BG-10", "argv": ["zig", "test", "build_support/identity_test.zig", "-OReleaseFast"], "required_inputs": [], "generated_outputs": []},
        {"id": "ci-boundaries", "phase": "BG-11", "argv": ["python3", "-m", "unittest", "scripts.tests.test_ci_cache_identity", "scripts.tests.test_ci_cache_admission", "scripts.tests.test_focused_ci_contract", "scripts.tests.test_architecture_ci_artifact", "scripts.tests.test_architecture_ci_trust", "scripts.tests.test_build_architecture_receipt"], "required_inputs": [], "generated_outputs": []},
        {"id": "benchmark-contract", "phase": "BG-12", "argv": ["python3", "scripts/check_benchmark_product_contract.py"], "required_inputs": ["conformance/benchmark-profiler-product-contract-v1.json"], "generated_outputs": []},
        {"id": "native-rust-oracle", "phase": "BG-13", "argv": ["python3", "scripts/e2e_interop.py", "--report-out", "{evidence_dir}/native-oracle.json", "--artifact-dir", "{evidence_dir}/native-oracle-artifacts", "--archive-dir", "{evidence_dir}/native-oracle-archive"], "required_inputs": [], "generated_outputs": ["{evidence_dir}/native-oracle.json"]},
        {"id": "riscv-anchor-validate", "phase": "BG-13", "argv": ["python3", "scripts/riscv_release_bundle.py", "verify-anchor", "--candidate", "{candidate}", "--workflow-sha", "{workflow_sha}", "--trust-context", "{riscv_trust_context}", "--policy-context", "{riscv_policy_context}", "--bundle", "{riscv_bundle}"], "required_inputs": ["{riscv_bundle}/manifest.json", "{riscv_bundle}/oracle-receipt.json", "{riscv_bundle}/release-gate.json", "{riscv_trust_context}", "{riscv_policy_context}"], "generated_outputs": []},
        {"id": "formal-performance-evidence", "phase": "BG-14", "argv": ["python3", "scripts/check_architecture_performance.py", "--role", "linux", "--baseline", "conformance/build-architecture-performance-baseline-v1/linux.json", "--output", "{evidence_dir}/performance.json"], "required_inputs": ["conformance/2026-07-19-build-monorepo-baseline-epoch-2-amendment.md", "conformance/build-architecture-performance-baseline-v1/linux.json"], "generated_outputs": ["{evidence_dir}/performance.json"]}
      ],
      "products": [
        {"product_id": "stwo-core", "phase": "BG-02", "identity_path": "zig-out/identity/stwo-core.json", "identity_command": null, "artifact_path": null},
        {"product_id": "stwo-native-cpu", "phase": "BG-04", "identity_path": null, "identity_command": "native-cpu-applications", "artifact_path": "zig-out/bin/stwo-zig-native-cpu"},
        {"product_id": "stwo-prover", "phase": "BG-02", "identity_path": "zig-out/identity/stwo-prover.json", "identity_command": null, "artifact_path": null},
        {"product_id": "stwo-riscv-cpu", "phase": "BG-03", "identity_path": null, "identity_command": "riscv-applications", "artifact_path": "zig-out/bin/stwo-zig-riscv-cpu"},
        {"product_id": "stwo-zig", "phase": "BG-08", "identity_path": "zig-out/identity/stwo-zig.json", "identity_command": null, "artifact_path": "zig-out/bin/stwo-zig"}
      ]
    },
    "macos": {
      "commands": [
        {"id": "baseline", "phase": "BG-00", "argv": ["python3", "scripts/check_build_monorepo_baseline.py"], "required_inputs": ["conformance/build-monorepo-baseline-v1.json"], "generated_outputs": []},
        {"id": "product-matrix", "phase": "BG-01", "argv": ["zig", "build", "product-matrix-identity", "-Doptimize=ReleaseFast"], "required_inputs": [], "generated_outputs": ["zig-out/identity/product-matrix.json"]},
        {"id": "core-prover", "phase": "BG-02", "argv": ["zig", "build", "test-stwo-core", "test-stwo-prover", "test-downstream-modules", "identity-stwo-core", "identity-stwo-prover", "-Doptimize=ReleaseFast"], "required_inputs": [], "generated_outputs": ["zig-out/identity/stwo-core.json", "zig-out/identity/stwo-prover.json"]},
        {"id": "native-cpu-product", "phase": "BG-04", "argv": ["zig", "build", "test-native-cpu-product", "stwo-native-cpu", "benchmark-native-cpu", "-Doptimize=ReleaseFast"], "required_inputs": [], "generated_outputs": ["zig-out/bin/stwo-zig-native-cpu", "zig-out/bin/stwo-zig-native-cpu-bench"]},
        {"id": "native-cpu-applications", "phase": "BG-04", "argv": ["zig-out/bin/stwo-zig-native-cpu", "applications"], "required_inputs": ["zig-out/bin/stwo-zig-native-cpu"], "generated_outputs": []},
        {"id": "native-cpu-link-closure", "phase": "BG-04", "argv": ["python3", "scripts/check_architecture_link_closure.py", "--product", "stwo-native-cpu", "--binary", "zig-out/bin/stwo-zig-native-cpu", "--output", "{evidence_dir}/native-cpu-link-closure.json"], "required_inputs": ["zig-out/bin/stwo-zig-native-cpu"], "generated_outputs": ["{evidence_dir}/native-cpu-link-closure.json"]},
        {"id": "native-metal-product", "phase": "BG-05", "argv": ["zig", "build", "test-native-metal", "stwo-native-metal", "native-proof-bench-metal", "metal-test", "-Doptimize=ReleaseFast"], "required_inputs": [], "generated_outputs": ["zig-out/bin/stwo-zig-native-metal", "zig-out/bin/native-proof-bench-metal"]},
        {"id": "native-metal-applications", "phase": "BG-05", "argv": ["zig-out/bin/stwo-zig-native-metal", "applications"], "required_inputs": ["zig-out/bin/stwo-zig-native-metal"], "generated_outputs": []},
        {"id": "native-metal-link-closure", "phase": "BG-05", "argv": ["python3", "scripts/check_architecture_link_closure.py", "--product", "stwo-native-metal", "--binary", "zig-out/bin/stwo-zig-native-metal", "--output", "{evidence_dir}/native-metal-link-closure.json"], "required_inputs": ["zig-out/bin/stwo-zig-native-metal"], "generated_outputs": ["{evidence_dir}/native-metal-link-closure.json"]},
        {"id": "native-metal-rust-oracle-build", "phase": "BG-05", "argv": ["cargo", "+nightly-2025-07-14", "build", "--release", "--locked", "--manifest-path", "tools/stwo-interop-rs/Cargo.toml"], "required_inputs": ["tools/stwo-interop-rs/Cargo.toml", "tools/stwo-interop-rs/Cargo.lock"], "generated_outputs": ["tools/stwo-interop-rs/target/release/stwo-interop-rs"]},
        {"id": "native-metal-oracle-matrix", "phase": "BG-05", "argv": ["python3", "scripts/native_proof_matrix.py", "--workload", "wide_fibonacci:log_n_rows=8,sequence_len=8", "--warmups", "0", "--samples", "1", "--protocol", "smoke", "--cooldown-seconds", "0", "--output-dir", "{evidence_dir}/native-metal-oracle", "--cpu-bin", "zig-out/bin/stwo-zig-native-cpu-bench", "--metal-bin", "zig-out/bin/native-proof-bench-metal", "--rust-oracle-bin", "tools/stwo-interop-rs/target/release/stwo-interop-rs", "--allow-non-headline"], "required_inputs": ["zig-out/bin/stwo-zig-native-cpu-bench", "zig-out/bin/native-proof-bench-metal", "tools/stwo-interop-rs/target/release/stwo-interop-rs"], "generated_outputs": ["{evidence_dir}/native-metal-oracle/summary.json"]},
        {"id": "metal-aot-builder", "phase": "BG-05", "argv": ["zig", "build", "metal-core-aot", "-Doptimize=ReleaseSafe"], "required_inputs": [], "generated_outputs": ["zig-out/bin/metal-core-aot"]},
        {"id": "metal-aot-receipt", "phase": "BG-05", "argv": ["python3", "scripts/metal_core_aot_receipt.py", "build", "--builder", "zig-out/bin/metal-core-aot", "--output-dir", "{evidence_dir}/metal-aot", "--receipt-out", "{evidence_dir}/metal-aot/receipt.json", "--commit", "{candidate}"], "required_inputs": ["zig-out/bin/metal-core-aot"], "generated_outputs": ["{evidence_dir}/metal-aot/receipt.json"]},
        {"id": "cuda-policy", "phase": "BG-06", "argv": ["zig", "test", "build_support/product_policy_test.zig", "-OReleaseFast"], "required_inputs": [], "generated_outputs": []},
        {"id": "deferred-products", "phase": "BG-07", "argv": ["zig", "test", "build_support/product_policy_test.zig", "-OReleaseFast"], "required_inputs": [], "generated_outputs": []},
        {"id": "aggregate", "phase": "BG-08", "argv": ["zig", "build", "stwo-zig", "test", "identity-stwo-zig", "-Daggregate-metal=false", "-Doptimize=ReleaseFast"], "required_inputs": [], "generated_outputs": ["zig-out/bin/stwo-zig", "zig-out/identity/stwo-zig.json"]},
        {"id": "aggregate-link-closure", "phase": "BG-08", "argv": ["python3", "scripts/check_architecture_link_closure.py", "--product", "stwo-zig", "--binary", "zig-out/bin/stwo-zig", "--output", "{evidence_dir}/aggregate-link-closure.json"], "required_inputs": ["zig-out/bin/stwo-zig"], "generated_outputs": ["{evidence_dir}/aggregate-link-closure.json"]},
        {"id": "focused-parity-prove", "phase": "BG-08", "argv": ["zig-out/bin/stwo-zig-native-cpu", "prove", "--example", "wide_fibonacci", "--log-n-rows", "8", "--sequence-len", "8", "--protocol", "smoke", "--profiled", "--output", "{evidence_dir}/focused-proof.json", "--report-out", "{evidence_dir}/focused-report.json"], "required_inputs": ["zig-out/bin/stwo-zig-native-cpu"], "generated_outputs": ["{evidence_dir}/focused-proof.json", "{evidence_dir}/focused-report.json"]},
        {"id": "aggregate-parity-prove", "phase": "BG-08", "argv": ["zig-out/bin/stwo-zig", "prove", "--air", "wide_fibonacci", "--backend", "cpu", "--log-n-rows", "8", "--sequence-len", "8", "--protocol", "smoke", "--profiled", "--output", "{evidence_dir}/aggregate-proof.json", "--report-out", "{evidence_dir}/aggregate-report.json"], "required_inputs": ["zig-out/bin/stwo-zig"], "generated_outputs": ["{evidence_dir}/aggregate-proof.json", "{evidence_dir}/aggregate-report.json"]},
        {"id": "focused-parity-verify", "phase": "BG-08", "argv": ["zig-out/bin/stwo-zig-native-cpu", "verify", "--artifact", "{evidence_dir}/focused-proof.json", "--protocol", "smoke"], "required_inputs": ["zig-out/bin/stwo-zig-native-cpu", "{evidence_dir}/focused-proof.json"], "generated_outputs": []},
        {"id": "aggregate-parity-verify", "phase": "BG-08", "argv": ["zig-out/bin/stwo-zig", "verify", "--artifact", "{evidence_dir}/aggregate-proof.json", "--protocol", "smoke"], "required_inputs": ["zig-out/bin/stwo-zig", "{evidence_dir}/aggregate-proof.json"], "generated_outputs": []},
        {"id": "aggregate-parity-compare", "phase": "BG-08", "argv": ["python3", "scripts/check_aggregate_parity.py", "--focused", "{evidence_dir}/focused-proof.json", "--aggregate", "{evidence_dir}/aggregate-proof.json", "--focused-report", "{evidence_dir}/focused-report.json", "--aggregate-report", "{evidence_dir}/aggregate-report.json", "--focused-verify", "{stdout_focused_parity_verify}", "--aggregate-verify", "{stdout_aggregate_parity_verify}", "--output", "{evidence_dir}/aggregate-parity.json"], "required_inputs": ["{evidence_dir}/focused-proof.json", "{evidence_dir}/aggregate-proof.json", "{evidence_dir}/focused-report.json", "{evidence_dir}/aggregate-report.json", "{stdout_focused_parity_verify}", "{stdout_aggregate_parity_verify}"], "generated_outputs": ["{evidence_dir}/aggregate-parity.json"]},
        {"id": "configure-closure", "phase": "BG-09", "argv": ["zig", "build", "build-configure-closure", "-Doptimize=ReleaseFast"], "required_inputs": [], "generated_outputs": ["zig-out/build-graph/configure-closure.json"]},
        {"id": "source-conformance", "phase": "BG-09", "argv": ["python3", "scripts/check_source_conformance.py"], "required_inputs": ["conformance/source-baseline.json"], "generated_outputs": []},
        {"id": "identity-mutations", "phase": "BG-10", "argv": ["zig", "test", "build_support/identity_test.zig", "-OReleaseFast"], "required_inputs": [], "generated_outputs": []},
        {"id": "ci-boundaries", "phase": "BG-11", "argv": ["python3", "-m", "unittest", "scripts.tests.test_ci_cache_identity", "scripts.tests.test_ci_cache_admission", "scripts.tests.test_focused_ci_contract", "scripts.tests.test_architecture_ci_artifact", "scripts.tests.test_architecture_ci_trust", "scripts.tests.test_build_architecture_receipt"], "required_inputs": [], "generated_outputs": []},
        {"id": "benchmark-contract", "phase": "BG-12", "argv": ["python3", "scripts/check_benchmark_product_contract.py"], "required_inputs": ["conformance/benchmark-profiler-product-contract-v1.json"], "generated_outputs": []},
        {"id": "native-rust-oracle", "phase": "BG-13", "argv": ["python3", "scripts/e2e_interop.py", "--report-out", "{evidence_dir}/native-oracle.json", "--artifact-dir", "{evidence_dir}/native-oracle-artifacts", "--archive-dir", "{evidence_dir}/native-oracle-archive"], "required_inputs": [], "generated_outputs": ["{evidence_dir}/native-oracle.json"]},
        {"id": "native-metal-formal-matrix", "phase": "BG-14", "argv": ["python3", "scripts/native_proof_matrix.py", "--warmups", "10", "--samples", "10", "--protocol", "functional", "--output-dir", "{evidence_dir}/native-matrix", "--cpu-bin", "zig-out/bin/stwo-zig-native-cpu-bench", "--metal-bin", "zig-out/bin/native-proof-bench-metal", "--rust-oracle-bin", "tools/stwo-interop-rs/target/release/stwo-interop-rs"], "required_inputs": ["conformance/build-architecture-performance-baseline-v1/macos.json", "zig-out/bin/stwo-zig-native-cpu-bench", "zig-out/bin/native-proof-bench-metal", "tools/stwo-interop-rs/target/release/stwo-interop-rs"], "generated_outputs": ["{evidence_dir}/native-matrix/summary.json"]},
        {"id": "formal-performance-evidence", "phase": "BG-14", "argv": ["python3", "scripts/check_architecture_performance.py", "--role", "macos", "--baseline", "conformance/build-architecture-performance-baseline-v1/macos.json", "--current", "{evidence_dir}/native-matrix/summary.json", "--output", "{evidence_dir}/performance.json"], "required_inputs": ["conformance/2026-07-19-build-monorepo-baseline-epoch-2-amendment.md", "conformance/build-architecture-performance-baseline-v1/macos.json", "{evidence_dir}/native-matrix/summary.json"], "generated_outputs": ["{evidence_dir}/performance.json"]}
      ],
      "products": [
        {"product_id": "stwo-core", "phase": "BG-02", "identity_path": "zig-out/identity/stwo-core.json", "identity_command": null, "artifact_path": null},
        {"product_id": "stwo-native-cpu", "phase": "BG-04", "identity_path": null, "identity_command": "native-cpu-applications", "artifact_path": "zig-out/bin/stwo-zig-native-cpu"},
        {"product_id": "stwo-native-metal", "phase": "BG-05", "identity_path": null, "identity_command": "native-metal-applications", "artifact_path": "zig-out/bin/stwo-zig-native-metal"},
        {"product_id": "stwo-prover", "phase": "BG-02", "identity_path": "zig-out/identity/stwo-prover.json", "identity_command": null, "artifact_path": null},
        {"product_id": "stwo-zig", "phase": "BG-08", "identity_path": "zig-out/identity/stwo-zig.json", "identity_command": null, "artifact_path": "zig-out/bin/stwo-zig"}
      ]
    }
  },
  "schema": "build-architecture-ci-plan-v1"
}
